justifytext/__init__.py
JustifyText-0.2.1.post3.dist-info/LICENSE.txt
JustifyText-0.2.1.post3.dist-info/METADATA
JustifyText-0.2.1.post3.dist-info/WHEEL
JustifyText-0.2.1.post3.dist-info/top_level.txt
JustifyText-0.2.1.post3.dist-info/RECORD
