Metadata-Version: 2.1
Name: JustifyText
Version: 0.2.1.post3
Summary: Returns list of strings *exactly* n width
Home-page: https://github.com/cjtx/JustifyText
Author: cjtx
Author-email: cjtx.code@gmail.com
License: Apache License 2.0
Keywords: justify string format
Platform: UNKNOWN
Classifier: Programming Language :: Python :: 3
Classifier: License :: OSI Approved :: Apache Software License
Classifier: Operating System :: OS Independent
